{"pageProps":{"keywords":["Spotted Scorpionfish","Bonaire","The Netherlands","portrait"],"photo":{"name":"DSC01646.jpg","key":"87de-0518","title":"Spotted Scorpionfish","description":"The scorpionfish is commonly found virtually invisible, blending in with the environment. Do not touch.","latin":"Scorpaena plumieri","location":"Bonaire, The Netherlands","tags":["2016","portrait"],"mode":"landscape","sizes":{"thumb":{"url":"https://s3.eu-central-1.amazonaws.com/splendid-nudibranch/87de-0518/thumb_DSC01646.jpg","width":220,"height":124},"xsmall":{"url":"https://s3.eu-central-1.amazonaws.com/splendid-nudibranch/87de-0518/xs_DSC01646.jpg","width":500,"height":281},"small":{"url":"https://s3.eu-central-1.amazonaws.com/splendid-nudibranch/87de-0518/s_DSC01646.jpg","width":1000,"height":563},"medium":{"url":"https://s3.eu-central-1.amazonaws.com/splendid-nudibranch/87de-0518/m_DSC01646.jpg","width":1400,"height":788},"large":{"url":"https://s3.eu-central-1.amazonaws.com/splendid-nudibranch/87de-0518/l_DSC01646.jpg","width":1900,"height":1069},"xlarge":{"url":"https://s3.eu-central-1.amazonaws.com/splendid-nudibranch/87de-0518/xl_DSC01646.jpg","width":2560,"height":1440}},"srcSet":"https://s3.eu-central-1.amazonaws.com/splendid-nudibranch/87de-0518/thumb_DSC01646.jpg 220w, https://s3.eu-central-1.amazonaws.com/splendid-nudibranch/87de-0518/xs_DSC01646.jpg 500w"}},"__N_SSG":true}